{
  "label": "Zendesk",
  "category_label": "Models",
  "branding": {
    "image_uri": "https://marketplace-api.looker.com/block-icons/zendesk.png",
    "tagline": "The Zendesk Block provides comprehensive analytics around customer support and satisfaction"
  },

  "constants": {
    "CONNECTION_NAME": {
      "label": "Connection Name",
      "value_constraint": "connection"
    },
    "SCHEMA_NAME": {
      "label": "Schema Name"
    },
    "CONFIG_PROJECT_NAME": {
      "label": "Config Project Name"
    },
    "ZENDESK_INSTANCE_DOMAIN": {
      "label": "Zendesk Instance Domain",
      "description": "Domain of your Zendesk instance (i.e. if looker.zendesk.com, then provide 'looker')"
    }
  },
  "models": [
    {
      "name": "block_zendesk",
      "connection_constant": "CONNECTION_NAME"
    }
  ],
  "auxiliary_projects": [
    {
      "git_uri": "git://github.com/looker/block-zendesk-config.git",
      "git_ref": "c29691e7c83fa5713abea477c1ac165fdd068444",
      "label": "Zendesk Config",
      "constant_name": "CONFIG_PROJECT_NAME"
    }
  ]
}
